Metadata-Version: 2.1
Name: github3.py
Version: 4.0.0
Summary: Python wrapper for the GitHub API(http://developer.github.com/v3)
Project-URL: Documentation, https://github3.readthedocs.io
Project-URL: Changelog, https://github3.readthedocs.io/en/latest/release-notes/index.html
Project-URL: Source, https://github.com/sigmavirus24/github3.py
Project-URL: Released Versions, https://github.com/sigmavirus24/github3.py/tags
Author-email: Ian Stapleton Cordasco <graffatcolmingov@gmail.com>
License-Expression: BSD-3-Clause
License-File: AUTHORS.rst
License-File: LICENSE
Classifier: Development Status :: 5 - Production/Stable
Classifier: Intended Audience :: Developers
Classifier: License :: OSI Approved
Classifier: License :: OSI Approved :: BSD License
Classifier: Programming Language :: Python
Classifier: Programming Language :: Python :: 3
Classifier: Programming Language :: Python :: 3 :: Only
Classifier: Programming Language :: Python :: Implementation :: CPython
Requires-Python: >=3.7
Requires-Dist: pyjwt[crypto]>=2.3.0
Requires-Dist: python-dateutil>=2.6.0
Requires-Dist: requests>=2.18
Requires-Dist: uritemplate>=3.0.0
Provides-Extra: dev
Requires-Dist: build; extra == 'dev'
Requires-Dist: github3-py[test]; extra == 'dev'
Requires-Dist: tox>=3.1.3; extra == 'dev'
Requires-Dist: twine; extra == 'dev'
Requires-Dist: wheel; extra == 'dev'
Provides-Extra: test
Requires-Dist: betamax-matchers>=0.3.0; extra == 'test'
Requires-Dist: betamax>=0.5.1; extra == 'test'
Requires-Dist: pytest-xdist[psutil]; extra == 'test'
Requires-Dist: pytest>=7.0; extra == 'test'
